SID/__init__.py
SID/fetch_image.py
SID/multidownload/FileManager.py
SID/multidownload/StateManager.py
SID/multidownload/__init__.py
SID/multidownload/constants.py
SID/multidownload/fetch_images.py
SID/utils/__init__.py
SID/utils/adjust_resolution.py
SID/utils/image_downloading.py
SID/utils/logger.py
SID/utils/prefs.py
SID/utils/providers.py
pysatimage-0.0.17.dist-info/LICENCE
pysatimage-0.0.17.dist-info/METADATA
pysatimage-0.0.17.dist-info/WHEEL
pysatimage-0.0.17.dist-info/top_level.txt
pysatimage-0.0.17.dist-info/RECORD
