Metadata-Version: 2.1
Name: pysatimage
Version: 0.0.17
Summary: SID: Satellite Imagery Downloader
Author-email: Artur Shevtsov <artorius.ua@gmail.com>
Project-URL: Homepage, https://github.com/artoriusss/sid
Project-URL: Issues, https://github.com/artoriusss/sid/issues
Classifier: Programming Language :: Python :: 3
Classifier: License :: OSI Approved :: MIT License
Classifier: Operating System :: OS Independent
Requires-Python: >=3.9
License-File: LICENCE
Requires-Dist: requests>=2.32.3
Requires-Dist: numpy>=2.0.0
Requires-Dist: opencv-python>=4.8.0
Requires-Dist: tqdm>=4.67.1
Requires-Dist: pyyaml>=6.0.2
Requires-Dist: setuptools>=75.7.0
